odoo/addons/account_accountant_reconcile/LICENSE
odoo/addons/account_accountant_reconcile/README.rst
odoo/addons/account_accountant_reconcile/__init__.py
odoo/addons/account_accountant_reconcile/__manifest__.py
odoo/addons/account_accountant_reconcile/demo/demo.xml
odoo/addons/account_accountant_reconcile/images/screen.png
odoo/addons/account_accountant_reconcile/models/__init__.py
odoo/addons/account_accountant_reconcile/models/account_bank_statement_line.py
odoo/addons/account_accountant_reconcile/static/description/icon.png
odoo/addons/account_accountant_reconcile/static/description/index.html
odoo/addons/account_accountant_reconcile/tests/TEST_INSTRUCTIONS.rst
odoo_addon_account_accountant_reconcile-18.0.1.0.0.dist-info/METADATA
odoo_addon_account_accountant_reconcile-18.0.1.0.0.dist-info/WHEEL
odoo_addon_account_accountant_reconcile-18.0.1.0.0.dist-info/top_level.txt
odoo_addon_account_accountant_reconcile-18.0.1.0.0.dist-info/RECORD
